betdaqlightweight/__init__.py
betdaqlightweight/client.py
betdaqlightweight/enums.py
betdaqlightweight/exceptions.py
betdaqlightweight/filters.py
betdaqlightweight/utils.py
betdaqlightweight/endpoints/__init__.py
betdaqlightweight/endpoints/base.py
betdaqlightweight/endpoints/readonly.py
betdaqlightweight/endpoints/secure.py
betdaqlightweight-0.1.0.dist-info/METADATA
betdaqlightweight-0.1.0.dist-info/RECORD
betdaqlightweight-0.1.0.dist-info/WHEEL
betdaqlightweight-0.1.0.dist-info/top_level.txt
examples/__init__.py
examples/readonly/__init__.py
examples/readonly/get_current_selection_sequence_number.py
examples/readonly/get_event_sub_tree_no_selection.py
examples/readonly/get_event_sub_tree_with_selection.py
examples/readonly/get_list_selections_changed_since.py
examples/readonly/get_market_information.py
examples/readonly/get_market_withdrawal_history.py
examples/readonly/get_odds_ladder.py
examples/readonly/get_prices.py
examples/readonly/get_sp_enabled_markets_information.py
examples/readonly/list_selection_trades.py
examples/readonly/list_top_events.py
examples/secure/__init__.py
examples/secure/cancel_all_orders.py
examples/secure/cancel_orders.py
examples/secure/cancel_orders_on_market.py
examples/secure/change_heartbeat.py
examples/secure/change_password.py
examples/secure/deregister_heartbeat.py
examples/secure/get_account_balances.py
examples/secure/get_order_details.py
examples/secure/list_account_postings.py
examples/secure/list_account_postings_by_id.py
examples/secure/list_blacklist_information.py
examples/secure/list_bootstrap_orders.py
examples/secure/list_orders_changed_since.py
examples/secure/place_orders_no_receipt.py
examples/secure/place_orders_with_receipt.py
examples/secure/pulse.py
examples/secure/register_heartbeat.py
examples/secure/suspend_all_orders.py
examples/secure/suspend_from_trading.py
examples/secure/suspend_orders.py
examples/secure/suspend_orders_by_market.py
examples/secure/unsuspend_from_trading.py
examples/secure/unsuspend_orders.py
examples/secure/update_orders_no_receipt.py
