Metadata-Version: 2.1
Name: betdaqlightweight
Version: 0.1.0
Summary: UNKNOWN
Home-page: https://github.com/bbezias/betdaqlightweight
Author: Benjamin Bezias
Author-email: benjaminbezias@gmail.com
License: GNU
Platform: UNKNOWN
Requires-Dist: suds-py3
